README.rst
setup.py
filestat/__init__.py
filestat/__main__.py
filestat/utils.py
filestat.egg-info/PKG-INFO
filestat.egg-info/SOURCES.txt
filestat.egg-info/dependency_links.txt
filestat.egg-info/not-zip-safe
filestat.egg-info/top_level.txt