Metadata-Version: 1.1
Name: filestat
Version: 0.2.3
Summary: A command line library for file monitoring.
Home-page: https://github.com/zxalif/filestat/
Author: Alif Jahan
Author-email: sajeeb162537@gmail.com
License: MIT
Keywords: filestat stats file monitoring details
Platform: UNKNOWN
Classifier: Development Status :: 4 - Beta
Classifier: Environment :: Console
Classifier: Intended Audience :: End Users/Desktop
Classifier: Intended Audience :: Developers
Classifier: Intended Audience :: Education
Classifier: Intended Audience :: System Administrators
Classifier: Operating System :: MacOS :: MacOS X
Classifier: Operating System :: POSIX
Classifier: Programming Language :: Python :: 3.5
Classifier: Programming Language :: Python :: 3.6
Classifier: Programming Language :: Python :: 3.7
Classifier: Programming Language :: Python :: 3.8
Classifier: Programming Language :: Python :: 3 :: Only
Classifier: Topic :: Office/Business
Classifier: Topic :: Software Development :: Bug Tracking
